Metadata-Version: 1.1
Name: code-sniffer
Version: 0.9.8
Summary: A command-line tool to check plagiarim in text and pdf
Home-page: https://dilawar.github.io/sniffer
Author: Dilawar Singh
Author-email: dilawars@ncbs.res.in
License: LGPL
Platform: UNKNOWN
Classifier: Development Status :: 5 - Production/Stable
Classifier: Intended Audience :: Developers
Classifier: Environment :: Console
Classifier: Programming Language :: Python
Classifier: Programming Language :: Python :: 2
Classifier: Programming Language :: Python :: 2.6
Classifier: Programming Language :: Python :: 2.7
Requires: Python (>=2.6)
